<?xml version="1.0" ?>
<annotation>
  <folder>VOC</folder>
  <filename>Capture d_écran 2025-06-12 223845.png</filename>
  <source>
    <database>roboflow.ai</database>
  </source>
  <size>
    <width>1867</width>
    <height>918</height>
    <depth>3</depth>
  </size>
  <segmented>0</segmented>
  <object>
    <name>person</name>
    <bndbox>
      <xmin>220</xmin>
      <ymin>275</ymin>
      <xmax>617</xmax>
      <ymax>914</ymax>
    </bndbox>
  </object>
  <object>
    <name>person</name>
    <bndbox>
      <xmin>1141</xmin>
      <ymin>210</ymin>
      <xmax>1863</xmax>
      <ymax>914</ymax>
    </bndbox>
  </object>
  <object>
    <name>person</name>
    <bndbox>
      <xmin>597</xmin>
      <ymin>243</ymin>
      <xmax>1275</xmax>
      <ymax>915</ymax>
    </bndbox>
  </object>
  <object>
    <name>person</name>
    <bndbox>
      <xmin>1293</xmin>
      <ymin>321</ymin>
      <xmax>1453</xmax>
      <ymax>556</ymax>
    </bndbox>
  </object>
  <object>
    <name>person</name>
    <bndbox>
      <xmin>1286</xmin>
      <ymin>334</ymin>
      <xmax>1372</xmax>
      <ymax>504</ymax>
    </bndbox>
  </object>
  <object>
    <name>person</name>
    <bndbox>
      <xmin>1709</xmin>
      <ymin>206</ymin>
      <xmax>1819</xmax>
      <ymax>364</ymax>
    </bndbox>
  </object>
  <object>
    <name>person</name>
    <bndbox>
      <xmin>1</xmin>
      <ymin>355</ymin>
      <xmax>182</xmax>
      <ymax>782</ymax>
    </bndbox>
  </object>
  <object>
    <name>person</name>
    <bndbox>
      <xmin>952</xmin>
      <ymin>219</ymin>
      <xmax>1082</xmax>
      <ymax>422</ymax>
    </bndbox>
  </object>
</annotation>
